{
  "image": [
    "CR2",
    "ai",
    "bmp",
    "eps",
    "exr",
    "gif",
    "ico",
    "jfif",
    "jpeg",
    "jpg",
    "png",
    "ps",
    "psd",
    "raw",
    "svg",
    "tif",
    "tiff"
  ],
  "audio": [
    "cda",
    "m3u",
    "mid",
    "midi",
    "mp3",
    "mpa",
    "ogg",
    "wav",
    "wma",
    "wpl"
  ],
  "text_files": [
    "doc",
    "docx",
    "md",
    "odt ",
    "pdf",
    "rtf",
    "tex",
    "txt",
    "wks ",
    "wpd",
    "wps"
  ],
  "video": [
    "3g2",
    "3gp",
    "avi",
    "flv",
    "h264",
    "m4v",
    "mkv",
    "mov",
    "mp4",
    "mpeg",
    "mpg",
    "rm",
    "swf",
    "vob",
    "wmv"
  ],
  "internet": [
    "asp",
    "aspx",
    "cer",
    "cfm",
    "cgi",
    "css",
    "htm",
    "js",
    "jsp",
    "part",
    "php",
    "pl",
    "rss",
    "sass",
    "scss",
    "xhtml"
  ],
  "compressed": [
    "7z",
    "arj",
    "deb",
    "gz",
    "pkg",
    "rar",
    "rpm",
    "tar",
    "tgz",
    "xz",
    "z",
    "zip"
  ],
  "disc": ["bin", "dmg", "iso", "toast", "vcd"],
  "data": [
    "csv",
    "dat",
    "db",
    "dbf",
    "json",
    "log",
    "mdb",
    "ods",
    "sav",
    "sql",
    "xlr",
    "xls",
    "xlsx",
    "xml"
  ],
  "executable": ["apk", "bat", "com", "exe", "gadget", "jar", "wsf"],
  "font": ["fnt", "fon", "otf", "ttf"],
  "presentation": ["key", "odp", "pps", "ppt", "pptx"],
  "system": [
    "bak",
    "cab",
    "cfg",
    "conf",
    "cpl",
    "cur",
    "dll",
    "dmp",
    "drv",
    "icns",
    "ini",
    "lnk",
    "msi",
    "sh",
    "sys",
    "tmp"
  ],
  "git": ["diff"],
  "vim": ["vba", "vim"]
}
